paf_sapgui_flows/__init__.py
paf_sapgui_flows/background_printing/__init__.py
paf_sapgui_flows/background_printing/immediately.py
paf_sapgui_flows/cic/__init__.py
paf_sapgui_flows/cic/msd_orders/__init__.py
paf_sapgui_flows/cic/msd_orders/aktionshistorie_bearbeiten
paf_sapgui_flows/cic/msd_orders/auftragsdaten_holen
paf_sapgui_flows/cic/msd_orders/beleg_buchen
paf_sapgui_flows/cic/msd_orders/brief_senden
paf_sapgui_flows/cic/msd_orders/fakturaperiodizität
paf_sapgui_flows/cic/msd_orders/kommunikationsdaten_ändern
paf_sapgui_flows/cic/msd_orders/kündigen
paf_sapgui_flows/cic/msd_orders/kündigung_stornieren
paf_sapgui_flows/cic/msd_orders/lieferadresse_ändern
paf_sapgui_flows/cic/msd_orders/löschen
paf_sapgui_flows/cic/msd_orders/objektwechsel
paf_sapgui_flows/cic/msd_orders/optIn_ändern
paf_sapgui_flows/cic/msd_orders/position_löschen
paf_sapgui_flows/cic/msd_orders/reklamation
paf_sapgui_flows/cic/msd_orders/selektiere_auftrag
paf_sapgui_flows/cic/msd_orders/stornieren
paf_sapgui_flows/cic/msd_orders/unbefristete_änderung
paf_sapgui_flows/cic/msd_orders/unterbrechung
paf_sapgui_flows/cic/msd_orders/wiederaufnahme
paf_sapgui_flows/cic/msd_orders/zahlweise
paf_sapgui_flows/cic/msd_orders/änderung_fakturamodalität
paf_sapgui_flows/cic/paf-sapgui-flow-cic.cs
paf_sapgui_flows/cic/position_details/__init__.py
paf_sapgui_flows/fi_keys/__init__.py
paf_sapgui_flows/fi_keys/close_keys/__init__.py
paf_sapgui_flows/fi_keys/close_keys/close_keys.py
paf_sapgui_flows/fi_keys/get_keys/__init__.py
paf_sapgui_flows/fi_keys/get_keys/get_keys.py
paf_sapgui_flows/fi_keys/paf_sapgui_flow_fi_keys.py
paf_sapgui_flows/order/__init__.py
paf_sapgui_flows/order/create/__init__.py
paf_sapgui_flows/order/create/checks/__init__.py
paf_sapgui_flows/order/create/checks/check.py
paf_sapgui_flows/order/create/checks/window_0.py
paf_sapgui_flows/order/create/checks/window_1.py
paf_sapgui_flows/order/create/create.py
paf_sapgui_flows/order/create/inputs.py
paf_sapgui_flows/order/create/object.py
paf_sapgui_flows-1.0.10.dist-info/WHEEL
paf_sapgui_flows-1.0.10.dist-info/METADATA
paf_sapgui_flows-1.0.10.dist-info/RECORD
