Metadata-Version: 2.1
Name: paf-sapgui-flows
Version: 1.0.10
Summary: 
Author: Your Name
Author-email: you@example.com
Requires-Python: >=3.10,<4.0
Classifier: Programming Language :: Python :: 3
Classifier: Programming Language :: Python :: 3.10
Requires-Dist: paf_sapgui_eltrans (>=1.0.8,<2.0.0)
